randapi.py
PyRANDAPI-1.0.0.dist-info/LICENSE
PyRANDAPI-1.0.0.dist-info/METADATA
PyRANDAPI-1.0.0.dist-info/WHEEL
PyRANDAPI-1.0.0.dist-info/top_level.txt
PyRANDAPI-1.0.0.dist-info/RECORD
